Metadata-Version: 1.0
Name: datadistribution
Version: 0.2
Summary: Calculate mean and standard devitaion based on data file
Home-page: UNKNOWN
Author: UNKNOWN
Author-email: UNKNOWN
License: UNKNOWN
Platform: UNKNOWN
